sha123/__init__.py
sha123/download_file.py
sha123-0.1.dist-info/LICENSE
sha123-0.1.dist-info/METADATA
sha123-0.1.dist-info/WHEEL
sha123-0.1.dist-info/entry_points.txt
sha123-0.1.dist-info/top_level.txt
sha123-0.1.dist-info/RECORD
